FreeLancing Projects Files/Quad_solver/Old_Quad/Quad_Solver/Quad_Solver.srcs/sources_1/new/quad_solver.v
`timescale 1ns / 1ps
//////////////////////////////////////////////////////////////////////////////////
// Company: 
// Engineer: 
// 
// Create Date: 12/06/2024 01:22:11 PM
// Design Name: 
// Module Name: quad_solver
// Project Name: 
// Target Devices: 
// Tool Versions: 
// Description: 
// 
// Dependencies: 
// 
// Revision:
// Revision 0.01 - File Created
// Additional Comments:
// 
//////////////////////////////////////////////////////////////////////////////////


module quad_solver
#(parameter WIDTH = 32, parameter SCALE = 12)
(input clk, reset, go, input signed [WIDTH-1:0] din, output reg signed [WIDTH-1:0] dout, output reg rdy);  
//    #(parameter WIDTH = 32, parameter SCALE = 16) 
//    (
//        input clk, 
//        input reset, 
//        input go, 
//        input signed [WIDTH-1:0] din, 
//        output reg signed [WIDTH-1:0] dout, 
//        output reg rdy
//    );

    // State encoding
    localparam IDLE = 4'b0000;
    localparam LOAD_A = 4'b0001;
    localparam LOAD_B = 4'b0010;
    localparam LOAD_C = 4'b0011;
    localparam CALC_DISCRIMINANT = 4'b0100;
    localparam CALC_DISCRIMINANT_ABS = 4'b1001;
    localparam CALC_SOLUTION = 4'b0101;
//    localparam CALC_SOLUTIONS_2 = 4'b0110;
    localparam OUTPUT_SOLUTIONS = 4'b0111;
    localparam BUFFER_STATE = 4'b1000;

    // Registers for FSM state
    reg [3:0] state, next_state;

    // Registers for coefficients and results
    reg signed [WIDTH-1-SCALE:0] a, b, c;
    reg signed [2*WIDTH-1:0] discriminant; // High precision for discriminant
    reg signed [WIDTH-1-SCALE:0] solution1_real, solution2_real;
    reg signed [WIDTH-1-SCALE:0] solution1_imag, solution2_imag;
    reg [3:0] output_counter; // Tracks output sequence
    reg signed [WIDTH-1-SCALE:0] din_scaled;

    // Square root calculation output
    wire signed [WIDTH-1:0] sqrt_result; // Square root output from the sqrt module
    wire signed [WIDTH-1:0] din_pos; // Square root output from the sqrt module
    reg [2*WIDTH-1:0] abs_discriminant; // Absolute value of discriminant
    wire sqrt_found;
    reg [3:0]counter_count = 4'd0;

    // Instantiate sqrt module
    sqrt #(2*WIDTH, WIDTH) sqrt_inst (
        .number(abs_discriminant),
        .root(sqrt_result),
        .found(sqrt_found)
    );

    // FSM: State transitions
    always @(negedge clk or posedge reset) begin
        if (reset) begin
            state <= IDLE;
        end else begin
            state <= next_state;
        end
    end

    // FSM: Next state logic
    always @(posedge clk) begin
        case (state)
            IDLE: 
                next_state = go ? LOAD_A : IDLE;

            LOAD_A: 
                next_state = BUFFER_STATE;
                
            BUFFER_STATE:
                next_state = LOAD_B;

            LOAD_B: 
                next_state = LOAD_C;

            LOAD_C: 
                next_state = CALC_DISCRIMINANT;

            CALC_DISCRIMINANT: 
                next_state = CALC_DISCRIMINANT_ABS;
                
            CALC_DISCRIMINANT_ABS:
                next_state = CALC_SOLUTION;

           
           CALC_SOLUTION: 
                next_state = OUTPUT_SOLUTIONS;

            OUTPUT_SOLUTIONS: 
                next_state = (output_counter == 5) ? IDLE : OUTPUT_SOLUTIONS;

            default: 
                next_state = IDLE;
        endcase
    end

    // FSM: Output logic and computation
    always @(posedge clk or posedge reset) begin
        if (reset) begin
            rdy <= 0;
            dout <= 0;
            output_counter <= 0;
        end else begin
            din_scaled <= din >> SCALE;
            case (state)
                IDLE: begin
                    rdy <= 0;
                    dout <= 0;
                    output_counter <= 0;
                end

                LOAD_A: begin
                    counter_count <= counter_count + 1;
                    if (din_scaled[WIDTH-1]) // Check the MSB for sign (assuming WIDTH-1 is the MSB)
                        a = -din_scaled;     // Negate if negative
                    else
                        a = din_scaled;      // Keep as is if positive
                end
                BUFFER_STATE:begin
                   if (din_scaled[WIDTH-1]) // Check the MSB for sign (assuming WIDTH-1 is the MSB)
                        a = -din_scaled;     // Negate if negative
                    else
                        a = din_scaled;      // Keep as is if positive
                end

                LOAD_B: begin
                   if (din_scaled[WIDTH-1]) // Check the MSB for sign (assuming WIDTH-1 is the MSB)
                        b = -din_scaled;     // Negate if negative
                    else
                        b = din_scaled;      // Keep as is if positive
                end

                LOAD_C: begin
                   if (din_scaled[WIDTH-1]) // Check the MSB for sign (assuming WIDTH-1 is the MSB)
                        c = -din_scaled;     // Negate if negative
                    else
                        c = din_scaled;      // Keep as is if positive
                end

                CALC_DISCRIMINANT: begin
                    discriminant <= (b * b) - (4 * a * c);
                    
                end
                
                CALC_DISCRIMINANT_ABS:begin
                    abs_discriminant <= (discriminant < 0) ? ((-discriminant)+1) : discriminant; // Get absolute value
                end

                CALC_SOLUTION: begin
                   if (discriminant >= 0) begin
                        solution1_real <= (-b + sqrt_result) /(2*a);
                        solution2_real <= (-b - sqrt_result)/(2*a);
                        solution1_imag <= 0;
                        solution2_imag <= 0;
                    end else begin
                        solution1_real <= -b / (2 * a);
                        solution2_real <= -b / (2 * a);
                        solution1_imag <= sqrt_result / (2 * a);
                        solution2_imag <= -sqrt_result / (2 * a);
                    end
                end

                OUTPUT_SOLUTIONS: begin
                    rdy <= 1;
                    if (solution1_real > solution2_real) begin
                        case (output_counter)
                            2'd0: dout <= solution2_real <<  SCALE;
                            2'd1: dout <= solution2_imag <<  SCALE;
                            2'd2: dout <= solution1_real <<  SCALE;
                            2'd3: dout <= solution1_imag <<  SCALE;
                        endcase
                        output_counter <= output_counter + 1;
                    end
                    else
                        begin
                            case (output_counter)
                                2'd0: dout <= solution1_real <<  SCALE;
                                2'd1: dout <= solution1_imag <<  SCALE;
                                2'd2: dout <= solution2_real <<  SCALE;
                                2'd3: dout <= solution2_imag <<  SCALE;
                            endcase
                            output_counter <= output_counter + 1;
                        end
                end
            endcase
        end
    end
endmodule



module sqrt #(
    parameter IN_WIDTH = 16,    // Width of the input number (default 16 bits)
    parameter OUT_WIDTH = 8     // Width of the output root (default 8 bits)
)(
    input [IN_WIDTH-1:0] number,  // Input number
    output reg [OUT_WIDTH-1:0] root, // Output square root
    output reg found
);
    // Internal registers for the binary search
    reg [OUT_WIDTH-1:0] low;       // Lower bound
    reg [OUT_WIDTH-1:0] high;      // Upper bound
    reg [OUT_WIDTH-1:0] mid;       // Midpoint
    reg [IN_WIDTH-1:0] mid_squared; // Midpoint squared
//    reg found;                     // Flag to indicate if the exact match is found

    always @(*) begin
        low = 0;
        high = (1 << OUT_WIDTH) - 1; // Maximum value for the output root width
        root = 0;
        found = 0;

        // Binary search algorithm
        while (low <= high && !found) begin
            mid = (low + high) >> 1; // Calculate mid
            mid_squared = mid * mid;

            if (mid_squared == number) begin
                root = mid; // Exact match
                found = 1;  // Set flag to exit the loop
            end
            else if (mid_squared < number) begin
                low = mid + 1; // Adjust lower bound
                root = mid;    // Update root to current mid
            end
            else begin
                high = mid - 1; // Adjust upper bound
            end
        end
    end
endmodule

FreeLancing Projects Files/Quad_solver/Old_Quad/Quad_Solver/Files/testbench.v
module testbench;

    // Parameters
    parameter WIDTH = 32;
    parameter SCALE = 16;
    parameter CLK_PERIOD = 10;  // Clock period in ns
    parameter MAX_TICKS = 100_000;  // Maximum clock ticks for simulation
    parameter NUM_TEST_CASES = 30;  // Number of test cases

    // Inputs to UUT
    reg clk;
    reg reset;
    reg go;
    reg signed [WIDTH-1:0] din;

    // Outputs from UUT
    wire signed [WIDTH-1:0] dout;
    wire rdy;

    // Debug flag
    reg debug = 1;

    // UUT instantiation
    quad_solver #(WIDTH, SCALE) uut (
        .clk(clk),
        .reset(reset),
        .go(go),
        .din(din),
        .dout(dout),
        .rdy(rdy)
    );

    // File handles
    integer test_case_file, result_file;
    integer test_case_number;
    integer ret; // Return value for $fscanf
    reg [WIDTH-1:0] a, b, c;
    reg [WIDTH-1:0] exp_r1, exp_im1, exp_r2, exp_im2;
    reg [WIDTH-1:0] obs_r1, obs_im1, obs_r2, obs_im2;

    // Clock tick counter and latency
    integer tick_count, start_tick, latency;
    integer successes;
    real total_latency, average_latency, final_score;

    // Clock generation
    initial begin
        clk = 0;
        forever #(CLK_PERIOD / 2) clk = ~clk;
    end

    // Simulation control
    initial begin
        // Open waveform file
        $dumpfile("testbench.vcd");
        $dumpvars(0, testbench);

        if (debug) $display("Opening test case and result files...");
        test_case_file = $fopen("test_cases.txt", "r");
        result_file = $fopen("test_results.txt", "w");

        if (test_case_file == 0 || result_file == 0) begin
            $display("Error: Unable to open test case or result file.");
            $stop;
        end

        // Write header to result file
        if (debug) $display("Writing header to result file...");
        $fwrite(result_file, "Test Case | Inputs (a, b, c) | Observed (r1, im1, r2, im2) | Expected (r1, im1, r2, im2) | Latency (cycles) | Result\n");

        // Initialize
        if (debug) $display("Initializing testbench...");
        @(negedge clk) reset = 1; go = 0; tick_count = 0; successes = 0; total_latency = 0;
        @(posedge clk);
        @(negedge clk) reset = 0;

        test_case_number = 0;

        while (!$feof(test_case_file)) begin
            @(negedge clk) go = 0;

            if (tick_count > MAX_TICKS) begin
                $display("Simulation exceeded maximum ticks (%0d). Aborting!", MAX_TICKS);
                $fclose(test_case_file);
                $fclose(result_file);
                $stop;
            end

            if (debug) $display("Reading test case #%0d...", test_case_number);
            ret = $fscanf(test_case_file, "%h, %h, %h, %h, %h, %h, %h\n", a, b, c, exp_r1, exp_im1, exp_r2, exp_im2);
            if (ret != 7) begin
                $display("Error: Incorrect format in test case file on line %0d", test_case_number + 1);
                $stop;
            end
            if (debug) $display("Test case #%0d read: a=%h, b=%h, c=%h, exp_r1=%h, exp_im1=%h, exp_r2=%h, exp_im2=%h",
                                test_case_number, a, b, c, exp_r1, exp_im1, exp_r2, exp_im2);

            // Apply inputs
            if (debug) $display("Applying inputs for test case #%0d...", test_case_number);
            @(negedge clk); go = 1;
            @(negedge clk) din = a;
            @(negedge clk) din = b;
            @(negedge clk) din = c;

            // Measure latency
            if (debug) $display("Measuring latency for test case #%0d...", test_case_number);
            start_tick = tick_count;
            wait (rdy == 1);
            latency = tick_count - start_tick;
            total_latency = total_latency + latency;
            if (debug) $display("Latency for test case #%0d: %0d cycles", test_case_number, latency);

            // Capture outputs
            if (debug) $display("Capturing outputs for test case #%0d...", test_case_number);
            @(negedge clk); obs_r1 = dout;
            @(negedge clk); obs_im1 = dout;
            @(negedge clk); obs_r2 = dout;
            @(negedge clk); obs_im2 = dout; 
            if (debug) $display("Observed outputs for test case #%0d: obs_r1=%h, obs_im1=%h, obs_r2=%h, obs_im2=%h",
                                test_case_number, obs_r1, obs_im1, obs_r2, obs_im2);

            // Compare observed vs. expected
            if (obs_r1 === exp_r1 && obs_im1 === exp_im1 &&
                obs_r2 === exp_r2 && obs_im2 === exp_im2) begin
                successes = successes + 1;
                $fwrite(result_file, "%0d | %h, %h, %h | %h, %h, %h, %h | %h, %h, %h, %h | %0d | Success\n",
                        test_case_number, a, b, c, obs_r1, obs_im1, obs_r2, obs_im2, exp_r1, exp_im1, exp_r2, exp_im2, latency);
                if (debug) $display("Test case #%0d passed.", test_case_number);
            end else begin
                $fwrite(result_file, "%0d | %h, %h, %h | %h, %h, %h, %h | %h, %h, %h, %h | %0d | Failure\n",
                        test_case_number, a, b, c, obs_r1, obs_im1, obs_r2, obs_im2, exp_r1, exp_im1, exp_r2, exp_im2, latency);
                if (debug) $display("Test case #%0d failed.", test_case_number);
            end

            test_case_number = test_case_number + 1;
        end

        // Calculate average latency
        if (debug) $display("Calculating average latency...");
        average_latency = total_latency / NUM_TEST_CASES;

        // Calculate final score
        if (debug) $display("Calculating final score...");
        final_score = (successes / (1.0 * NUM_TEST_CASES)) * 50.0 + (50.0 / (average_latency + 1));

        // Print final results
        $display("Number of successes: %0d", successes);
        $display("Average latency: %0.2f cycles", average_latency);
        $display("Final score: %0.2f", final_score);

        // Close files
        if (debug) $display("Closing files...");
        $fclose(test_case_file);
        $fclose(result_file);

        // Finish simulation
        $display("Testbench completed. Results written to test_results.txt.");
        $finish;
    end

    // Tick counter logic
    always @(posedge clk) begin
        tick_count = tick_count + 1;
        if (tick_count > MAX_TICKS) begin
            $display("Simulation exceeded maximum ticks (%0d). Aborting!", MAX_TICKS);
            $finish;
        end
    end
endmodule

FreeLancing Projects Files/Quad_solver/Old_Quad/Quad_Solver/Quad_Solver.sim/sim_1/behav/xsim/testbench.vcd
$date
   Sun Dec  8 19:10:54 2024
$end
$version
  2019.1
$end
$timescale
  1ps
$end
$scope module testbench $end
$var reg 1 ! clk $end
$var reg 1 " reset $end
$var reg 1 # go $end
$var reg 32 $ din [31:0] $end
$var wire 32 % dout [31:0] $end
$var wire 1 & rdy $end
$var reg 1 ' debug $end
$var integer 32 ( test_case_file $end
$var integer 32 ) result_file $end
$var integer 32 * test_case_number $end
$var integer 32 + ret $end
$var reg 32 , a [31:0] $end
$var reg 32 - b [31:0] $end
$var reg 32 . c [31:0] $end
$var reg 32 / exp_r1 [31:0] $end
$var reg 32 0 exp_im1 [31:0] $end
$var reg 32 1 exp_r2 [31:0] $end
$var reg 32 2 exp_im2 [31:0] $end
$var reg 32 3 obs_r1 [31:0] $end
$var reg 32 4 obs_im1 [31:0] $end
$var reg 32 5 obs_r2 [31:0] $end
$var reg 32 6 obs_im2 [31:0] $end
$var integer 32 7 tick_count $end
$var integer 32 8 start_tick $end
$var integer 32 9 latency $end
$var integer 32 : successes $end
$var real 32 ; total_latency $end
$var real 32 < average_latency $end
$var real 32 = final_score $end
$var parameter 32 > WIDTH [31:0] $end
$var parameter 32 ? SCALE [31:0] $end
$var parameter 32 @ CLK_PERIOD [31:0] $end
$var parameter 32 A MAX_TICKS [31:0] $end
$var parameter 32 B NUM_TEST_CASES [31:0] $end
$scope module uut $end
$var wire 1 C clk $end
$var wire 1 D reset $end
$var wire 1 E go $end
$var wire 32 F din [31:0] $end
$var reg 32 G dout [31:0] $end
$var reg 1 H rdy $end
$var reg 4 I state [3:0] $end
$var reg 4 J next_state [3:0] $end
$var reg 16 K a [15:0] $end
$var reg 16 L b [15:0] $end
$var reg 16 M c [15:0] $end
$var reg 64 N discriminant [63:0] $end
$var reg 16 O solution1_real [15:0] $end
$var reg 16 P solution2_real [15:0] $end
$var reg 16 Q solution1_imag [15:0] $end
$var reg 16 R solution2_imag [15:0] $end
$var reg 4 S output_counter [3:0] $end
$var reg 16 T din_scaled [15:0] $end
$var wire 32 U sqrt_result [31:0] $end
$var wire 32 V din_pos [31:0] $end
$var reg 64 W abs_discriminant [63:0] $end
$var wire 1 X sqrt_found $end
$var reg 4 Y counter_count [3:0] $end
$var parameter 32 Z WIDTH [31:0] $end
$var parameter 32 [ SCALE [31:0] $end
$var parameter 4 \ IDLE [3:0] $end
$var parameter 4 ] LOAD_A [3:0] $end
$var parameter 4 ^ LOAD_B [3:0] $end
$var parameter 4 _ LOAD_C [3:0] $end
$var parameter 4 ` CALC_DISCRIMINANT [3:0] $end
$var parameter 4 a CALC_DISCRIMINANT_ABS [3:0] $end
$var parameter 4 b CALC_SOLUTION [3:0] $end
$var parameter 4 c OUTPUT_SOLUTIONS [3:0] $end
$var parameter 4 d BUFFER_STATE [3:0] $end
$scope module sqrt_inst $end
$var wire 64 e number [63:0] $end
$var reg 32 f root [31:0] $end
$var reg 1 g found $end
$var reg 32 h low [31:0] $end
$var reg 32 i high [31:0] $end
$var reg 32 j mid [31:0] $end
$var reg 64 k mid_squared [63:0] $end
$var parameter 32 l IN_WIDTH [31:0] $end
$var parameter 32 m OUT_WIDTH [31:0] $end
$upscope $end
$upscope $end
$upscope $end
$enddefinitions $end
#0
$dumpvars
0!
x"
x#
bx $
bx %
x&
1'
b11111111111111111011000111100000 (
b11111111111111111011000111100001 )
bx *
bx +
bx ,
bx -
bx .
bx /
bx 0
bx 1
bx 2
bx 3
bx 4
bx 5
bx 6
bx 7
bx 8
bx 9
bx :
r0 ;
r0 <
r0 =
b100000 >
b10000 ?
b1010 @
b11000011010100000 A
b11110 B
0C
xD
xE
bx F
bx G
xH
bx I
b0 J
bx K
bx L
bx M
bx N
bx O
bx P
bx Q
bx R
bx S
bx T
bx U
bz V
bx W
xX
b0 Y
b100000 Z
b10000 [
b0 \
b1 ]
b10 ^
b11 _
b100 `
b1001 a
b101 b
b111 c
b1000 d
bx e
bx f
xg
bx h
bx i
bx j
bx k
b1000000 l
b100000 m
$end
#5000
1!
1C
#10000
0!
1"
0#
b0 %
0&
b0 7
b0 :
0C
1D
0E
b0 G
0H
b0 I
b0 S
#15000
1!
b1 7
1C
#20000
0!
0"
b0 *
0C
0D
#25000
1!
b10 7
1C
#30000
0!
b111 +
b10000000000000000 ,
b11111111111111110000000000000000 -
b11111111111111100000000000000000 .
b11111111111111110000000000000000 /
b0 0
b100000000000000000 1
b0 2
0C
#35000
1!
b11 7
1C
#40000
0!
1#
0C
1E
b1 J
#45000
1!
b100 7
1C
#50000
0!
b10000000000000000 $
0C
b10000000000000000 F
b1 I
#55000
1!
b101 7
1C
b1 T
b1 Y
#60000
0!
b11111111111111110000000000000000 $
0C
b11111111111111110000000000000000 F
b1000 J
#65000
1!
b110 7
1C
b1 K
b1111111111111111 T
b10 Y
#70000
0!
b11111111111111100000000000000000 $
b110 8
0C
b11111111111111100000000000000000 F
b1000 I
#75000
1!
b111 7
1C
b1111111111111111 K
b1111111111111110 T
#80000
0!
0C
b10 J
#85000
1!
b1000 7
1C
b1111111111111110 K
#90000
0!
0C
b10 I
#95000
1!
b1001 7
1C
b1111111111111110 L
#100000
0!
0C
b11 J
#105000
1!
b1010 7
1C
#110000
0!
0C
b11 I
#115000
1!
b1011 7
1C
b1111111111111110 M
#120000
0!
0C
b100 J
#125000
1!
b1100 7
1C
#130000
0!
0C
b100 I
#135000
1!
b1101 7
1C
b1111111111111111111111111111111111111111111111111111111111110100 N
#140000
0!
0C
b1001 J
#145000
1!
b1110 7
1C
#150000
0!
0C
b1001 I
#155000
1!
b1111 7
1C
b11 U
b1101 W
0X
b1101 e
b11 f
0g
b100 h
b11 i
b100 j
b10000 k
#160000
0!
0C
b101 J
#165000
1!
b10000 7
1C
#170000
0!
0C
b101 I
#175000
1!
b10001 7
1C
b0 O
b0 P
b0 Q
b0 R
#180000
0!
0C
b111 J
#185000
1!
b10010 7
1C
#190000
0!
0C
b111 I
#195000
1!
1&
b10011 7
b1101 9
r13 ;
1C
1H
b1 S
#200000
0!
b0 3
0C
#205000
1!
b10100 7
1C
b10 S
#210000
0!
b0 4
0C
#215000
1!
b10101 7
1C
b11 S
#220000
0!
b0 5
0C
#225000
1!
b10110 7
1C
b100 S
#230000
0!
b1 *
b0 6
0C
#235000
1!
b10111 7
1C
b101 S
#240000
0!
0#
b11111111101001100000000000000000 .
b11111111111101110000000000000000 /
b10100000000000000000 1
0C
0E
b0 J
#245000
1!
b11000 7
1C
b110 S
#250000
0!
1#
0C
1E
b0 I
b111 J
#255000
1!
0&
b11001 7
1C
0H
b0 S
#260000
0!
b10000000000000000 $
0C
b10000000000000000 F
b111 I
b1 J
#265000
1!
1&
b11010 7
1C
1H
b1 S
b1 T
#270000
0!
b11111111111111110000000000000000 $
0C
b11111111111111110000000000000000 F
b1 I
b111 J
#275000
1!
b11011 7
1C
b1 K
b1111111111111111 T
b11 Y
#280000
0!
b11111111101001100000000000000000 $
b11011 8
b0 9
0C
b11111111101001100000000000000000 F
b111 I
b1000 J
#285000
1!
b11100 7
1C
b10 S
b1111111110100110 T
#290000
0!
0C
b1000 I
b111 J
#295000
1!
b11101 7
1C
b1111111110100110 K
#300000
0!
0C
b111 I
b10 J
#305000
1!
b11110 7
1C
b11 S
#310000
0!
0C
b10 I
b111 J
#315000
1!
b11111 7
1C
b1111111110100110 L
#320000
0!
b10 *
0C
b111 I
b11 J
#325000
1!
b100000 7
1C
b100 S
#330000
0!
0#
b11111111110101100000000000000000 .
b11111111111110100000000000000000 /
b1110000000000000000 1
0C
0E
b11 I
b111 J
#335000
1!
b100001 7
1C
b1111111110100110 M
#340000
0!
1#
0C
1E
b111 I
b100 J
#345000
1!
b100010 7
1C
b101 S
#350000
0!
b10000000000000000 $
0C
b10000000000000000 F
b100 I
b0 J
#355000
1!
b100011 7
1C
b1111111111111111111111111111111111111111111111111010000100010100 N
b1 T
#360000
0!
b11111111111111110000000000000000 $
0C
b11111111111111110000000000000000 F
b0 I
b1001 J
#365000
1!
0&
b100100 7
1C
0H
b0 S
b1111111111111111 T
#370000
0!
b11111111110101100000000000000000 $
b100100 8
0C
b11111111110101100000000000000000 F
b1001 I
b1 J
#375000
1!
b100101 7
1C
b1111111111010110 T
b10011011 U
b101111011101101 W
b101111011101101 e
b10011011 f
0g
b10011100 h
b10011011 i
b10011100 j
b101111100010000 k
#380000
0!
0C
b1 I
b101 J
#385000
1!
b100110 7
1C
b1111111111010110 K
b100 Y
#390000
0!
0C
b101 I
b1000 J
#395000
1!
b100111 7
1C
b1111111111111111 O
b1111111111111111 P
b1111111111111111 Q
b1 R
#400000
0!
0C
b1000 I
b111 J
#405000
1!
b101000 7
1C
#410000
0!
0C
b111 I
b10 J
#415000
1!
b11111111111111110000000000000000 %
1&
b101001 7
b101 9
r18 ;
1C
b11111111111111110000000000000000 G
1H
b1 S
#420000
0!
b11111111111111110000000000000000 3
0C
b10 I
b111 J
#425000
1!
b101010 7
1C
b1111111111010110 L
#430000
0!
b11111111111111110000000000000000 4
0C
b111 I
b11 J
#435000
1!
b101011 7
1C
b10 S
#440000
0!
b11111111111111110000000000000000 5
0C
b11 I
b111 J
#445000
1!
b101100 7
1C
b1111111111010110 M
#450000
0!
b11 *
b11111111111111110000000000000000 6
0C
b111 I
b100 J
#455000
1!
b101101 7
1C
b11 S
#460000
0!
0#
b11110000000000000000 -
b1101100000000000000000 .
b11111111111101110000000000000000 /
b11111111111110100000000000000000 1
0C
0E
b100 I
b111 J
#465000
1!
b101110 7
1C
b1111111111111111111111111111111111111111111111111110101101010100 N
#470000
0!
1#
0C
1E
b111 I
b1001 J
#475000
1!
b10000000000000000 %
b101111 7
1C
b10000000000000000 G
b100 S
#480000
0!
b10000000000000000 $
0C
b10000000000000000 F
b1001 I
b111 J
#485000
1!
b110000 7
1C
b1 T
b1001000 U
b1010010101101 W
b1010010101101 e
b1001000 f
0g
b1001001 h
b1001000 i
b1001000 j
b1010001000000 k
#490000
0!
b11110000000000000000 $
0C
b11110000000000000000 F
b111 I
b101 J
#495000
1!
b110001 7
1C
b101 S
b1111 T
#500000
0!
b1101100000000000000000 $
b110001 8
b0 9
0C
b1101100000000000000000 F
b101 I
b0 J
#505000
1!
b110010 7
1C
b0 O
b0 P
b0 Q
b0 R
b110110 T
#510000
0!
b10000000000000000 3
0C
b0 I
b111 J
#515000
1!
b0 %
0&
b110011 7
1C
b0 G
0H
b0 S
#520000
0!
b0 4
0C
b111 I
b1 J
#525000
1!
1&
b110100 7
1C
1H
b1 S
#530000
0!
b0 5
0C
b1 I
b111 J
#535000
1!
b110101 7
1C
b110110 K
b101 Y
#540000
0!
b100 *
b0 6
0C
b111 I
b1000 J
#545000
1!
b110110 7
1C
b10 S
#550000
0!
0#
b11111111111111000000000000000000 -
b11111111111000000000000000000000 .
b11111111111111000000000000000000 /
b10000000000000000000 1
0C
0E
b1000 I
b111 J
#555000
1!
b110111 7
1C
#560000
0!
1#
0C
1E
b111 I
b10 J
#565000
1!
b111000 7
1C
b11 S
#570000
0!
b10000000000000000 $
0C
b10000000000000000 F
b10 I
b111 J
#575000
1!
b111001 7
1C
b110110 L
b1 T
#580000
0!
b11111111111111000000000000000000 $
0C
b11111111111111000000000000000000 F
b111 I
b11 J
#585000
1!
b111010 7
1C
b100 S
b1111111111111100 T
#590000
0!
b11111111111000000000000000000000 $
b111010 8
0C
b11111111111000000000000000000000 F
b11 I
b111 J
#595000
1!
b111011 7
1C
b1111111111111100 M
b1111111111100000 T
#600000
0!
b0 3
0C
b111 I
b100 J
#605000
1!
b111100 7
1C
b101 S
#610000
0!
0C
b100 I
b0 J
#615000
1!
b111101 7
1C
b111011000100 N
#620000
0!
0C
b0 I
b1001 J
#625000
1!
0&
b111110 7
1C
0H
b0 S
#630000
0!
b101 *
0C
b1001 I
b1 J
#635000
1!
b111111 7
1C
b111101 U
b111011000100 W
b111011000100 e
b111101 f
0g
b111110 h
b111101 i
b111110 j
b111100000100 k
#640000
0!
0#
b11111111111101100000000000000000 -
b110000000000000000000 .
b1000000000000000000 /
b1100000000000000000 1
0C
0E
b1 I
b101 J
#645000
1!
b1000000 7
1C
b1111111111100000 K
b110 Y
#650000
0!
1#
0C
1E
b101 I
b1000 J
#655000
1!
b1000001 7
1C
b1 P
#660000
0!
b10000000000000000 $
0C
b10000000000000000 F
b1000 I
b111 J
#665000
1!
b1000010 7
1C
b1 T
#670000
0!
b11111111111101100000000000000000 $
0C
b11111111111101100000000000000000 F
b111 I
b10 J
#675000
1!
1&
b1000011 7
1C
1H
b1 S
b1111111111110110 T
#680000
0!
b110000000000000000000 $
b1000011 8
0C
b110000000000000000000 F
b10 I
b111 J
#685000
1!
b1000100 7
1C
b1111111111110110 L
b11000 T
#690000
0!
0C
b111 I
b11 J
#695000
1!
b1000101 7
1C
b10 S
#700000
0!
0C
b11 I
b111 J
#705000
1!
b1000110 7
1C
b11000 M
#710000
0!
0C
b111 I
b100 J
#715000
1!
b10000000000000000 %
b1000111 7
1C
b10000000000000000 G
b11 S
#720000
0!
b110 *
b10000000000000000 6
0C
b100 I
b111 J
#725000
1!
b1001000 7
1C
b110001100100 N
#730000
0!
0#
b11111111111110100000000000000000 -
b1010000000000000000 .
b10000000000000000 /
b1010000000000000000 1
0C
0E
b111 I
b1001 J
#735000
1!
b0 %
b1001001 7
1C
b0 G
b100 S
#740000
0!
1#
0C
1E
b1001 I
b111 J
#745000
1!
b1001010 7
1C
b111000 U
b110001100100 W
b110001100100 e
b111000 f
0g
b111001 h
b111000 i
b111000 j
b110001000000 k
#750000
0!
b10000000000000000 $
0C
b10000000000000000 F
b111 I
b101 J
#755000
1!
b1001011 7
1C
b101 S
b1 T
#760000
0!
b11111111111110100000000000000000 $
0C
b11111111111110100000000000000000 F
b101 I
b0 J
#765000
1!
b1001100 7
1C
b1111111111111111 O
b0 P
b1111111111111010 T
#770000
0!
b1010000000000000000 $
b1001100 8
0C
b1010000000000000000 F
b0 I
b111 J
#775000
1!
0&
b1001101 7
1C
0H
b0 S
b101 T
#780000
0!
0C
b111 I
b1 J
#785000
1!
b11111111111111110000000000000000 %
1&
b1001110 7
1C
b11111111111111110000000000000000 G
1H
b1 S
#790000
0!
b11111111111111110000000000000000 4
0C
b1 I
b111 J
#795000
1!
b1001111 7
1C
b101 K
b111 Y
#800000
0!
b11111111111111110000000000000000 5
0C
b111 I
b1000 J
#805000
1!
b0 %
b1010000 7
1C
b0 G
b10 S
#810000
0!
b111 *
b0 6
0C
b1000 I
b111 J
#815000
1!
b1010001 7
1C
#820000
0!
0#
0C
0E
b111 I
b10 J
#825000
1!
b1010010 7
1C
b11 S
#830000
0!
1#
0C
1E
b10 I
b111 J
#835000
1!
b1010011 7
1C
b101 L
#840000
0!
b10000000000000000 $
0C
b10000000000000000 F
b111 I
b11 J
#845000
1!
b1010100 7
1C
b100 S
b1 T
#850000
0!
b11111111111110100000000000000000 $
0C
b11111111111110100000000000000000 F
b11 I
b111 J
#855000
1!
b1010101 7
1C
b1 M
b1111111111111010 T
#860000
0!
b1010000000000000000 $
b1010101 8
0C
b1010000000000000000 F
b111 I
b100 J
#865000
1!
b1010110 7
1C
b101 S
b101 T
#870000
0!
0C
b100 I
b0 J
#875000
1!
b1010111 7
1C
b101 N
#880000
0!
b0 4
0C
b0 I
b1001 J
#885000
1!
0&
b1011000 7
1C
0H
b0 S
#890000
0!
b0 5
0C
b1001 I
b1 J
#895000
1!
b1011001 7
1C
b10 U
b101 W
b101 e
b10 f
0g
b11 h
b10 i
b10 j
b100 k
#900000
0!
b1000 *
0C
b1 I
b101 J
#905000
1!
b1011010 7
1C
b1000 Y
#910000
0!
0#
b11111111111110010000000000000000 -
b11111111111011100000000000000000 .
b11111111111111100000000000000000 /
b10010000000000000000 1
0C
0E
b101 I
b1000 J
#915000
1!
b1011011 7
1C
b0 O
#920000
0!
1#
0C
1E
b1000 I
b111 J
#925000
1!
b1011100 7
1C
#930000
0!
b10000000000000000 $
0C
b10000000000000000 F
b111 I
b10 J
#935000
1!
1&
b1011101 7
1C
1H
b1 S
b1 T
#940000
0!
b11111111111110010000000000000000 $
0C
b11111111111110010000000000000000 F
b10 I
b111 J
#945000
1!
b1011110 7
1C
b1 L
b1111111111111001 T
#950000
0!
b11111111111011100000000000000000 $
b1011110 8
0C
b11111111111011100000000000000000 F
b111 I
b11 J
#955000
1!
b1011111 7
1C
b10 S
b1111111111101110 T
#960000
0!
0C
b11 I
b111 J
#965000
1!
b1100000 7
1C
b1111111111101110 M
#970000
0!
0C
b111 I
b100 J
#975000
1!
b1100001 7
1C
b11 S
#980000
0!
0C
b100 I
b111 J
#985000
1!
b1100010 7
1C
b101101001 N
#990000
0!
b1001 *
0C
b111 I
b1001 J
#995000
1!
b1100011 7
1C
b100 S
#1000000
0!
0#
b11111111111110100000000000000000 -
b1010000000000000000 .
b10000000000000000 /
b1010000000000000000 1
0C
0E
b1001 I
b111 J
