FreeLancing Projects Files/Quad_solver/Quad_Solver/Quad_Solver.srcs/sources_1/new/quad_solver.v
`timescale 1ns / 1ps
//////////////////////////////////////////////////////////////////////////////////
// Company: 
// Engineer: 
// 
// Create Date: 12/08/2024 05:26:03 PM
// Design Name: 
// Module Name: quad_solver_2
// Project Name: 
// Target Devices: 
// Tool Versions: 
// Description: 
// 
// Dependencies: 
// 
// Revision:
// Revision 0.01 - File Created
// Additional Comments:
// 
//////////////////////////////////////////////////////////////////////////////////



module quad_solver
#(parameter WIDTH = 32, parameter SCALE = 12)
(input clk, reset, go, input signed [WIDTH-1:0] din, output wire signed [WIDTH-1:0] dout, output reg rdy);  

    // State encoding
    localparam IDLE = 3'b000;
    localparam LOAD_A = 3'b001;
    localparam LOAD_B = 3'b011;
    localparam OUTPUT_COUNTER_STATE = 3'b100;
    localparam BUFFER_STATE = 3'b010;

    // Registers for FSM state
    reg [3:0] state;

    // Registers for coefficients and results
    reg signed [WIDTH-1-SCALE:0] a, b, c;
    reg signed [2*WIDTH-1:0] discriminant; // High precision for discriminant
    reg signed [WIDTH-1-SCALE:0] solution1_real, solution2_real;
    reg signed [WIDTH-1-SCALE:0] solution1_imag, solution2_imag;
    reg [3:0] output_counter = 1; // Tracks output sequence
    reg signed [WIDTH-1-SCALE:0] din_scaled;
    reg [WIDTH-1:0] low;       // Lower bound
    reg [WIDTH-1:0] high;      // Upper bound
    reg [WIDTH-1:0] mid;       // Midpoint
    reg [2*WIDTH-1:0] mid_squared; // Midpoint squaredroot
    reg found;
    reg loop_ready = 0;

    // Square root calculation output
    reg signed [WIDTH-1:0] sqrt_result; // Square root output from the sqrt module
    wire signed [WIDTH-1:0] din_pos; // Square root output from the sqrt module
    reg [2*WIDTH-1:0] abs_discriminant; // Absolute value of discriminant
    wire sqrt_found;
    reg [3:0]counter_count = 4'd0;
    reg inv_seq = 0;
    reg goes_baby = 0; 


    // FSM: State transitions
    always @(negedge clk or posedge reset) begin
        if (reset) begin
            state <= IDLE;
        end else begin
            case (state)
                IDLE: 
                    state <= go ? LOAD_A : IDLE;
    
                LOAD_A: 
                    state <= BUFFER_STATE;
                    
                BUFFER_STATE:
                    state <= LOAD_B;
    
                LOAD_B: 
                    state <= OUTPUT_COUNTER_STATE;
                
                OUTPUT_COUNTER_STATE:
                    state <= (output_counter == 4) ? IDLE : OUTPUT_COUNTER_STATE;
                default: 
                    state <= IDLE;
            endcase
        end
    end

    // FSM: Output logic and computation
    always @(negedge clk or negedge reset) begin
        if (reset) begin
            rdy <= 0;
//            dout <= 0;
            output_counter <= 0;
        end else begin
            din_scaled <= din >> SCALE;
            case (state)
                IDLE: begin
                    rdy <= 0;
//                    dout <= 0;
                    output_counter <= 1;
                end

                LOAD_A: begin
                    counter_count <= counter_count + 1;
                    if (din_scaled[WIDTH-1]) // Check the MSB for sign (assuming WIDTH-1 is the MSB)
                        a <= -din_scaled;     // Negate if negative
                    else
                        a <= din_scaled;      // Keep as is if positive
                end
                BUFFER_STATE:begin
                   if (din_scaled[WIDTH-1]) 
                        a <= -din_scaled;     
                    else
                        a <= din_scaled;      
                end

                LOAD_B: begin
                   if (din_scaled[WIDTH-1]) begin
                        b <= -din_scaled;
                        goes_baby <= 1;
                   end     
                   else begin
                        b <= din_scaled;
                        goes_baby <= 1;
                   end      
                end

                OUTPUT_COUNTER_STATE:begin
                    if (output_counter > 3) begin
                        output_counter <= 1;
                        rdy <= 0;
                    end
                    else begin
                        output_counter <= output_counter + 1;
                    end
                end
                    
            endcase
        end
    end
 always@(*) begin
        if(goes_baby) begin
            while(~rdy)
                    begin
                        if (din_scaled[WIDTH-1]) 
                            c = -din_scaled;     
                        else
                            c = din_scaled;
                        discriminant = (b * b) - (4 * a * c);
                        abs_discriminant = (discriminant < 0) ? -discriminant : discriminant;
                        
                        low = 0;
                        high = (1 << WIDTH) - 1; // Maximum value for the output root width
                        sqrt_result = 0;
                        found = 0;
                        while (low <= high && !found) begin
                            mid = (low + high) >> 1; // Calculate mid
                            mid_squared = mid * mid;
                
                            if (mid_squared == abs_discriminant) begin
                                sqrt_result = mid; // Exact match
                                found = 1;  // Set flag to exit the loop
                            end
                            else if (mid_squared < abs_discriminant) begin
                                low = mid + 1; // Adjust lower bound
                                sqrt_result = mid;    // Update root to current mid
                            end
                            else begin
                                high = mid - 1; // Adjust upper bound
                            end
                        end
                        if (discriminant >= 0) begin
                            solution1_real = (-b + sqrt_result) /(2*a);
                            solution2_real = (-b - sqrt_result)/(2*a);
                            solution1_imag = 0;
                            solution2_imag = 0;
                        end else begin
                            solution1_real = -b / (2 * a);
                            solution2_real = -b / (2 * a);
                            solution1_imag = sqrt_result / (2 * a);
                            solution2_imag = -sqrt_result / (2 * a);
                        end
                        if (solution1_real > solution2_real) begin
                            inv_seq = 1;
                        end
                        else begin
                            inv_seq = 0;
                         end
                        rdy = 1;
                        goes_baby = 0;
                end
         end
 end
 assign dout = rdy ? ~inv_seq? output_counter == 1? (solution1_real << SCALE) : output_counter == 2? (solution1_imag << SCALE): output_counter == 3 ? (solution2_real << SCALE) : output_counter ==4 ? (solution2_imag << SCALE) : 0 :output_counter == 1? (solution2_real << SCALE) : output_counter == 2? (solution2_imag << SCALE): output_counter == 3 ? (solution1_real << SCALE) : output_counter ==4 ? (solution1_imag << SCALE) : 0 : 0;
endmodule

FreeLancing Projects Files/Quad_solver/Quad_Solver/Files/testbench.v
module testbench;

    // Parameters
    parameter WIDTH = 32;
    parameter SCALE = 16;
    parameter CLK_PERIOD = 10;  // Clock period in ns
    parameter MAX_TICKS = 100_000;  // Maximum clock ticks for simulation
    parameter NUM_TEST_CASES = 30;  // Number of test cases

    // Inputs to UUT
    reg clk;
    reg reset;
    reg go;
    reg signed [WIDTH-1:0] din;

    // Outputs from UUT
    wire signed [WIDTH-1:0] dout;
    wire rdy;

    // Debug flag
    reg debug = 1;

    // UUT instantiation
    quad_solver #(WIDTH, SCALE) uut (
        .clk(clk),
        .reset(reset),
        .go(go),
        .din(din),
        .dout(dout),
        .rdy(rdy)
    );

    // File handles
    integer test_case_file, result_file;
    integer test_case_number;
    integer ret; // Return value for $fscanf
    reg [WIDTH-1:0] a, b, c;
    reg [WIDTH-1:0] exp_r1, exp_im1, exp_r2, exp_im2;
    reg [WIDTH-1:0] obs_r1, obs_im1, obs_r2, obs_im2;

    // Clock tick counter and latency
    integer tick_count, start_tick, latency;
    integer successes;
    real total_latency, average_latency, final_score;

    // Clock generation
    initial begin
        clk = 0;
        forever #(CLK_PERIOD / 2) clk = ~clk;
    end

    // Simulation control
    initial begin
        // Open waveform file
        $dumpfile("testbench.vcd");
        $dumpvars(0, testbench);

        if (debug) $display("Opening test case and result files...");
        test_case_file = $fopen("test_cases.txt", "r");
        result_file = $fopen("test_results.txt", "w");

        if (test_case_file == 0 || result_file == 0) begin
            $display("Error: Unable to open test case or result file.");
            $stop;
        end

        // Write header to result file
        if (debug) $display("Writing header to result file...");
        $fwrite(result_file, "Test Case | Inputs (a, b, c) | Observed (r1, im1, r2, im2) | Expected (r1, im1, r2, im2) | Latency (cycles) | Result\n");

        // Initialize
        if (debug) $display("Initializing testbench...");
        @(negedge clk) reset = 1; go = 0; tick_count = 0; successes = 0; total_latency = 0;
        @(posedge clk);
        @(negedge clk) reset = 0;

        test_case_number = 0;

        while (!$feof(test_case_file)) begin
            @(negedge clk) go = 0;

            if (tick_count > MAX_TICKS) begin
                $display("Simulation exceeded maximum ticks (%0d). Aborting!", MAX_TICKS);
                $fclose(test_case_file);
                $fclose(result_file);
                $stop;
            end

            if (debug) $display("Reading test case #%0d...", test_case_number);
            ret = $fscanf(test_case_file, "%h, %h, %h, %h, %h, %h, %h\n", a, b, c, exp_r1, exp_im1, exp_r2, exp_im2);
            if (ret != 7) begin
                $display("Error: Incorrect format in test case file on line %0d", test_case_number + 1);
                $stop;
            end
            if (debug) $display("Test case #%0d read: a=%h, b=%h, c=%h, exp_r1=%h, exp_im1=%h, exp_r2=%h, exp_im2=%h",
                                test_case_number, a, b, c, exp_r1, exp_im1, exp_r2, exp_im2);

            // Apply inputs
            if (debug) $display("Applying inputs for test case #%0d...", test_case_number);
            @(negedge clk) din = a; go = 1;
            @(negedge clk);
            @(negedge clk) din = b;
            @(negedge clk) din = c;

            // Measure latency
            if (debug) $display("Measuring latency for test case #%0d...", test_case_number);
            start_tick = tick_count;
            wait (rdy == 1);
            latency = tick_count - start_tick;
            total_latency = total_latency + latency;
            if (debug) $display("Latency for test case #%0d: %0d cycles", test_case_number, latency);

            // Capture outputs
            if (debug) $display("Capturing outputs for test case #%0d...", test_case_number);
            @(negedge clk); obs_r1 = dout;
            @(negedge clk); obs_im1 = dout;
            @(negedge clk); obs_r2 = dout;
            @(negedge clk); obs_im2 = dout; 
            if (debug) $display("Observed outputs for test case #%0d: obs_r1=%h, obs_im1=%h, obs_r2=%h, obs_im2=%h",
                                test_case_number, obs_r1, obs_im1, obs_r2, obs_im2);

            // Compare observed vs. expected
            if (obs_r1 === exp_r1 && obs_im1 === exp_im1 &&
                obs_r2 === exp_r2 && obs_im2 === exp_im2) begin
                successes = successes + 1;
                $fwrite(result_file, "%0d | %h, %h, %h | %h, %h, %h, %h | %h, %h, %h, %h | %0d | Success\n",
                        test_case_number, a, b, c, obs_r1, obs_im1, obs_r2, obs_im2, exp_r1, exp_im1, exp_r2, exp_im2, latency);
                if (debug) $display("Test case #%0d passed.", test_case_number);
            end else begin
                $fwrite(result_file, "%0d | %h, %h, %h | %h, %h, %h, %h | %h, %h, %h, %h | %0d | Failure\n",
                        test_case_number, a, b, c, obs_r1, obs_im1, obs_r2, obs_im2, exp_r1, exp_im1, exp_r2, exp_im2, latency);
                if (debug) $display("Test case #%0d failed.", test_case_number);
            end

            test_case_number = test_case_number + 1;
        end

        // Calculate average latency
        if (debug) $display("Calculating average latency...");
        average_latency = total_latency / NUM_TEST_CASES;

        // Calculate final score
        if (debug) $display("Calculating final score...");
        final_score = (successes / (1.0 * NUM_TEST_CASES)) * 50.0 + (50.0 / (average_latency + 1));

        // Print final results
        $display("Number of successes: %0d", successes);
        $display("Average latency: %0.2f cycles", average_latency);
        $display("Final score: %0.2f", final_score);

        // Close files
        if (debug) $display("Closing files...");
        $fclose(test_case_file);
        $fclose(result_file);

        // Finish simulation
        $display("Testbench completed. Results written to test_results.txt.");
        $finish;
    end

    // Tick counter logic
    always @(posedge clk) begin
        tick_count = tick_count + 1;
        if (tick_count > MAX_TICKS) begin
            $display("Simulation exceeded maximum ticks (%0d). Aborting!", MAX_TICKS);
            $finish;
        end
    end
endmodule

FreeLancing Projects Files/Quad_solver/Quad_Solver/Quad_Solver.sim/sim_1/behav/xsim/testbench.vcd
$date
   Sun Dec  8 20:49:59 2024
$end
$version
  2019.1
$end
$timescale
  1ps
$end
$scope module testbench $end
$var reg 1 ! clk $end
$var reg 1 " reset $end
$var reg 1 # go $end
$var reg 32 $ din [31:0] $end
$var wire 32 % dout [31:0] $end
$var wire 1 & rdy $end
$var reg 1 ' debug $end
$var integer 32 ( test_case_file $end
$var integer 32 ) result_file $end
$var integer 32 * test_case_number $end
$var integer 32 + ret $end
$var reg 32 , a [31:0] $end
$var reg 32 - b [31:0] $end
$var reg 32 . c [31:0] $end
$var reg 32 / exp_r1 [31:0] $end
$var reg 32 0 exp_im1 [31:0] $end
$var reg 32 1 exp_r2 [31:0] $end
$var reg 32 2 exp_im2 [31:0] $end
$var reg 32 3 obs_r1 [31:0] $end
$var reg 32 4 obs_im1 [31:0] $end
$var reg 32 5 obs_r2 [31:0] $end
$var reg 32 6 obs_im2 [31:0] $end
$var integer 32 7 tick_count $end
$var integer 32 8 start_tick $end
$var integer 32 9 latency $end
$var integer 32 : successes $end
$var real 32 ; total_latency $end
$var real 32 < average_latency $end
$var real 32 = final_score $end
$var parameter 32 > WIDTH [31:0] $end
$var parameter 32 ? SCALE [31:0] $end
$var parameter 32 @ CLK_PERIOD [31:0] $end
$var parameter 32 A MAX_TICKS [31:0] $end
$var parameter 32 B NUM_TEST_CASES [31:0] $end
$scope module uut $end
$var wire 1 C clk $end
$var wire 1 D reset $end
$var wire 1 E go $end
$var wire 32 F din [31:0] $end
$var wire 32 % dout [31:0] $end
$var reg 1 G rdy $end
$var reg 4 H state [3:0] $end
$var reg 16 I a [15:0] $end
$var reg 16 J b [15:0] $end
$var reg 16 K c [15:0] $end
$var reg 64 L discriminant [63:0] $end
$var reg 16 M solution1_real [15:0] $end
$var reg 16 N solution2_real [15:0] $end
$var reg 16 O solution1_imag [15:0] $end
$var reg 16 P solution2_imag [15:0] $end
$var reg 4 Q output_counter [3:0] $end
$var reg 16 R din_scaled [15:0] $end
$var reg 32 S low [31:0] $end
$var reg 32 T high [31:0] $end
$var reg 32 U mid [31:0] $end
$var reg 64 V mid_squared [63:0] $end
$var reg 1 W found $end
$var reg 1 X loop_ready $end
$var reg 32 Y sqrt_result [31:0] $end
$var wire 32 Z din_pos [31:0] $end
$var reg 64 [ abs_discriminant [63:0] $end
$var wire 1 \ sqrt_found $end
$var reg 4 ] counter_count [3:0] $end
$var reg 1 ^ inv_seq $end
$var reg 1 _ goes_baby $end
$var parameter 32 ` WIDTH [31:0] $end
$var parameter 32 a SCALE [31:0] $end
$var parameter 3 b IDLE [2:0] $end
$var parameter 3 c LOAD_A [2:0] $end
$var parameter 3 d LOAD_B [2:0] $end
$var parameter 3 e OUTPUT_COUNTER_STATE [2:0] $end
$var parameter 3 f BUFFER_STATE [2:0] $end
$upscope $end
$upscope $end
$enddefinitions $end
#0
$dumpvars
0!
x"
x#
bx $
bx0000000000000000 %
x&
1'
b11111111111111111011000111100000 (
b11111111111111111011000111100001 )
bx *
bx +
bx ,
bx -
bx .
bx /
bx 0
bx 1
bx 2
bx 3
bx 4
bx 5
bx 6
bx 7
bx 8
bx 9
bx :
r0 ;
r0 <
r0 =
b100000 >
b10000 ?
b1010 @
b11000011010100000 A
b11110 B
0C
xD
xE
bx F
xG
b0 H
bx I
bx J
bx K
bx L
bx M
bx N
bx O
bx P
b1 Q
bx R
bx S
bx T
bx U
bx V
xW
0X
bx Y
bz Z
bx [
z\
b0 ]
0^
0_
b100000 `
b10000 a
b0 b
b1 c
b11 d
b100 e
b10 f
$end
#5000
1!
1C
#10000
0!
1"
0#
b0 %
0&
b0 7
b0 :
0C
1D
0E
0G
b0 Q
#15000
1!
b1 7
1C
#20000
0!
0"
b0 *
0C
0D
0G
b1 Q
#25000
1!
b10 7
1C
#30000
0!
b111 +
b10000000000000000 ,
b11111111111111110000000000000000 -
b11111111111111100000000000000000 .
b11111111111111110000000000000000 /
b0 0
b100000000000000000 1
b0 2
0C
0G
b1 Q
#35000
1!
b11 7
1C
#40000
0!
1#
b10000000000000000 $
0C
1E
b10000000000000000 F
0G
b1 H
b1 Q
b1 R
#45000
1!
b100 7
1C
#50000
0!
0C
b10 H
b1 I
b1 ]
#55000
1!
b101 7
1C
#60000
0!
b11111111111111110000000000000000 $
0C
b11111111111111110000000000000000 F
b11 H
b1111111111111111 R
#65000
1!
b110 7
1C
#70000
0!
b11111111111111100000000000000000 $
b11111111111111110000000000000000 %
1&
b110 8
b0 9
0C
b11111111111111100000000000000000 F
1G
b100 H
b1111111111111111 J
b1111111111111110 K
b1001 L
b10 M
b1111111111111111 N
b0 O
b0 P
b1111111111111110 R
b0 S
b110 T
b11 U
b1001 V
1W
b11 Y
b1001 [
1^
0_
#75000
1!
b111 7
1C
#80000
0!
b0 %
b11111111111111110000000000000000 3
0C
b10 Q
#85000
1!
b1000 7
1C
#90000
0!
b100000000000000000 %
b0 4
0C
b11 Q
#95000
1!
b1001 7
1C
#100000
0!
b0 %
b100000000000000000 5
0C
b100 Q
#105000
1!
b1010 7
1C
#110000
0!
0&
b1 *
b0 6
b1 :
0C
0G
b0 H
b1 Q
#115000
1!
b1011 7
1C
#120000
0!
0#
b11111111101001100000000000000000 .
b11111111111101110000000000000000 /
b10100000000000000000 1
0C
0E
0G
b1 Q
#125000
1!
b1100 7
1C
#130000
0!
1#
b10000000000000000 $
0C
1E
b10000000000000000 F
0G
b1 H
b1 Q
b1 R
#135000
1!
b1101 7
1C
#140000
0!
0C
b10 H
b10 ]
#145000
1!
b1110 7
1C
#150000
0!
b11111111111111110000000000000000 $
0C
b11111111111111110000000000000000 F
b11 H
b1111111111111111 R
#155000
1!
b1111 7
1C
#160000
0!
b11111111101001100000000000000000 $
b11111111111101110000000000000000 %
1&
b1111 8
0C
b11111111101001100000000000000000 F
1G
b100 H
b1111111110100110 K
b101101001 L
b1010 M
b1111111111110111 N
b0 O
b0 P
b1111111110100110 R
b10000 S
b10110 T
b10011 U
b101101001 V
1W
b10011 Y
b101101001 [
0_
#165000
1!
b10000 7
1C
#170000
0!
b0 %
b11111111111101110000000000000000 3
0C
b10 Q
#175000
1!
b10001 7
1C
#180000
0!
b10100000000000000000 %
0C
b11 Q
#185000
1!
b10010 7
1C
#190000
0!
b0 %
b10100000000000000000 5
0C
b100 Q
#195000
1!
b10011 7
1C
#200000
0!
0&
b10 *
b10 :
0C
0G
b0 H
b1 Q
#205000
1!
b10100 7
1C
#210000
0!
0#
b11111111110101100000000000000000 .
b11111111111110100000000000000000 /
b1110000000000000000 1
0C
0E
0G
b1 Q
#215000
1!
b10101 7
1C
#220000
0!
1#
b10000000000000000 $
0C
1E
b10000000000000000 F
0G
b1 H
b1 Q
b1 R
#225000
1!
b10110 7
1C
#230000
0!
0C
b10 H
b11 ]
#235000
1!
b10111 7
1C
#240000
0!
b11111111111111110000000000000000 $
0C
b11111111111111110000000000000000 F
b11 H
b1111111111111111 R
#245000
1!
b11000 7
1C
#250000
0!
b11111111110101100000000000000000 $
b11111111111110100000000000000000 %
1&
b11000 8
0C
b11111111110101100000000000000000 F
1G
b100 H
b1111111111010110 K
b10101001 L
b111 M
b1111111111111010 N
b0 O
b0 P
b1111111111010110 R
b1100 S
b1110 T
b1101 U
b10101001 V
1W
b1101 Y
b10101001 [
0_
#255000
1!
b11001 7
1C
#260000
0!
b0 %
b11111111111110100000000000000000 3
0C
b10 Q
#265000
1!
b11010 7
1C
#270000
0!
b1110000000000000000 %
0C
b11 Q
#275000
1!
b11011 7
1C
#280000
0!
b0 %
b1110000000000000000 5
0C
b100 Q
#285000
1!
b11100 7
1C
#290000
0!
0&
b11 *
b11 :
0C
0G
b0 H
b1 Q
#295000
1!
b11101 7
1C
#300000
0!
0#
b11110000000000000000 -
b1101100000000000000000 .
b11111111111101110000000000000000 /
b11111111111110100000000000000000 1
0C
0E
0G
b1 Q
#305000
1!
b11110 7
1C
#310000
0!
1#
b10000000000000000 $
0C
1E
b10000000000000000 F
0G
b1 H
b1 Q
b1 R
#315000
1!
b11111 7
1C
#320000
0!
0C
b10 H
b100 ]
#325000
1!
b100000 7
1C
#330000
0!
b11110000000000000000 $
0C
b11110000000000000000 F
b11 H
b1111 R
#335000
1!
b100001 7
1C
#340000
0!
b1101100000000000000000 $
b11111111111101110000000000000000 %
1&
b100001 8
0C
b1101100000000000000000 F
1G
b100 H
b1111 J
b110110 K
b1001 L
b1111111111111010 M
b1111111111110111 N
b0 O
b0 P
b110110 R
b0 S
b110 T
b11 U
b1001 V
1W
b11 Y
b1001 [
0_
#345000
1!
b100010 7
1C
#350000
0!
b0 %
b11111111111101110000000000000000 3
0C
b10 Q
#355000
1!
b100011 7
1C
#360000
0!
b11111111111110100000000000000000 %
0C
b11 Q
#365000
1!
b100100 7
1C
#370000
0!
b0 %
b11111111111110100000000000000000 5
0C
b100 Q
#375000
1!
b100101 7
1C
#380000
0!
0&
b100 *
b100 :
0C
0G
b0 H
b1 Q
#385000
1!
b100110 7
1C
#390000
0!
0#
b11111111111111000000000000000000 -
b11111111111000000000000000000000 .
b11111111111111000000000000000000 /
b10000000000000000000 1
0C
0E
0G
b1 Q
#395000
1!
b100111 7
1C
#400000
0!
1#
b10000000000000000 $
0C
1E
b10000000000000000 F
0G
b1 H
b1 Q
b1 R
#405000
1!
b101000 7
1C
#410000
0!
0C
b10 H
b101 ]
#415000
1!
b101001 7
1C
#420000
0!
b11111111111111000000000000000000 $
0C
b11111111111111000000000000000000 F
b11 H
b1111111111111100 R
#425000
1!
b101010 7
1C
#430000
0!
b11111111111000000000000000000000 $
b11111111111111000000000000000000 %
1&
b101010 8
0C
b11111111111000000000000000000000 F
1G
b100 H
b1111111111111100 J
b1111111111100000 K
b10010000 L
b1000 M
b1111111111111100 N
b0 O
b0 P
b1111111111100000 R
b1100 S
b1100 T
b1100 U
b10010000 V
1W
b1100 Y
b10010000 [
0_
#435000
1!
b101011 7
1C
#440000
0!
b0 %
b11111111111111000000000000000000 3
0C
b10 Q
#445000
1!
b101100 7
1C
#450000
0!
b10000000000000000000 %
0C
b11 Q
#455000
1!
b101101 7
1C
#460000
0!
b0 %
b10000000000000000000 5
0C
b100 Q
#465000
1!
b101110 7
1C
#470000
0!
0&
b101 *
b101 :
0C
0G
b0 H
b1 Q
#475000
1!
b101111 7
1C
#480000
0!
0#
b11111111111101100000000000000000 -
b110000000000000000000 .
b1000000000000000000 /
b1100000000000000000 1
0C
0E
0G
b1 Q
#485000
1!
b110000 7
1C
#490000
0!
1#
b10000000000000000 $
0C
1E
b10000000000000000 F
0G
b1 H
b1 Q
b1 R
#495000
1!
b110001 7
1C
#500000
0!
0C
b10 H
b110 ]
#505000
1!
b110010 7
1C
#510000
0!
b11111111111101100000000000000000 $
0C
b11111111111101100000000000000000 F
b11 H
b1111111111110110 R
#515000
1!
b110011 7
1C
#520000
0!
b110000000000000000000 $
b1000000000000000000 %
1&
b110011 8
0C
b110000000000000000000 F
1G
b100 H
b1111111111110110 J
b11000 K
b100 L
b110 M
b100 N
b0 O
b0 P
b11000 R
b10 S
b10 T
b10 U
b100 V
1W
b10 Y
b100 [
0_
#525000
1!
b110100 7
1C
#530000
0!
b0 %
b1000000000000000000 3
0C
b10 Q
#535000
1!
b110101 7
1C
#540000
0!
b1100000000000000000 %
0C
b11 Q
#545000
1!
b110110 7
1C
#550000
0!
b0 %
b1100000000000000000 5
0C
b100 Q
#555000
1!
b110111 7
1C
#560000
0!
0&
b110 *
b110 :
0C
0G
b0 H
b1 Q
#565000
1!
b111000 7
1C
#570000
0!
0#
b11111111111110100000000000000000 -
b1010000000000000000 .
b10000000000000000 /
b1010000000000000000 1
0C
0E
0G
b1 Q
#575000
1!
b111001 7
1C
#580000
0!
1#
b10000000000000000 $
0C
1E
b10000000000000000 F
0G
b1 H
b1 Q
b1 R
#585000
1!
b111010 7
1C
#590000
0!
0C
b10 H
b111 ]
#595000
1!
b111011 7
1C
#600000
0!
b11111111111110100000000000000000 $
0C
b11111111111110100000000000000000 F
b11 H
b1111111111111010 R
#605000
1!
b111100 7
1C
#610000
0!
b1010000000000000000 $
b10000000000000000 %
1&
b111100 8
0C
b1010000000000000000 F
1G
b100 H
b1111111111111010 J
b101 K
b10000 L
b101 M
b1 N
b0 O
b0 P
b101 R
b100 S
b100 T
b100 U
b10000 V
1W
b100 Y
b10000 [
0_
#615000
1!
b111101 7
1C
#620000
0!
b0 %
b10000000000000000 3
0C
b10 Q
#625000
1!
b111110 7
1C
#630000
0!
b1010000000000000000 %
0C
b11 Q
#635000
1!
b111111 7
1C
#640000
0!
b0 %
b1010000000000000000 5
0C
b100 Q
#645000
1!
b1000000 7
1C
#650000
0!
0&
b111 *
b111 :
0C
0G
b0 H
b1 Q
#655000
1!
b1000001 7
1C
#660000
0!
0#
0C
0E
0G
b1 Q
#665000
1!
b1000010 7
1C
#670000
0!
1#
b10000000000000000 $
0C
1E
b10000000000000000 F
0G
b1 H
b1 Q
b1 R
#675000
1!
b1000011 7
1C
#680000
0!
0C
b10 H
b1000 ]
#685000
1!
b1000100 7
1C
#690000
0!
b11111111111110100000000000000000 $
0C
b11111111111110100000000000000000 F
b11 H
b1111111111111010 R
#695000
1!
b1000101 7
1C
#700000
0!
b1010000000000000000 $
b10000000000000000 %
1&
b1000101 8
0C
b1010000000000000000 F
1G
b100 H
b101 K
b10000 L
b101 M
b1 N
b0 O
b0 P
b101 R
b100 S
b100 T
b100 U
b10000 V
1W
b100 Y
b10000 [
0_
#705000
1!
b1000110 7
1C
#710000
0!
b0 %
0C
b10 Q
#715000
1!
b1000111 7
1C
#720000
0!
b1010000000000000000 %
0C
b11 Q
#725000
1!
b1001000 7
1C
#730000
0!
b0 %
0C
b100 Q
#735000
1!
b1001001 7
1C
#740000
0!
0&
b1000 *
b1000 :
0C
0G
b0 H
b1 Q
#745000
1!
b1001010 7
1C
#750000
0!
0#
b11111111111110010000000000000000 -
b11111111111011100000000000000000 .
b11111111111111100000000000000000 /
b10010000000000000000 1
0C
0E
0G
b1 Q
#755000
1!
b1001011 7
1C
#760000
0!
1#
b10000000000000000 $
0C
1E
b10000000000000000 F
0G
b1 H
b1 Q
b1 R
#765000
1!
b1001100 7
1C
#770000
0!
0C
b10 H
b1001 ]
#775000
1!
b1001101 7
1C
#780000
0!
b11111111111110010000000000000000 $
0C
b11111111111110010000000000000000 F
b11 H
b1111111111111001 R
#785000
1!
b1001110 7
1C
#790000
0!
b11111111111011100000000000000000 $
b11111111111111100000000000000000 %
1&
b1001110 8
0C
b11111111111011100000000000000000 F
1G
b100 H
b1111111111111001 J
b1111111111101110 K
b1111001 L
b1001 M
b1111111111111110 N
b0 O
b0 P
b1111111111101110 R
b1000 S
b1110 T
b1011 U
b1111001 V
1W
b1011 Y
b1111001 [
0_
#795000
1!
b1001111 7
1C
#800000
0!
b0 %
b11111111111111100000000000000000 3
0C
b10 Q
#805000
1!
b1010000 7
1C
#810000
0!
b10010000000000000000 %
0C
b11 Q
#815000
1!
b1010001 7
1C
#820000
0!
b0 %
b10010000000000000000 5
0C
b100 Q
#825000
1!
b1010010 7
1C
#830000
0!
0&
b1001 *
b1001 :
0C
0G
b0 H
b1 Q
#835000
1!
b1010011 7
1C
#840000
0!
0#
b11111111111110100000000000000000 -
b1010000000000000000 .
b10000000000000000 /
b1010000000000000000 1
0C
0E
0G
b1 Q
#845000
1!
b1010100 7
1C
#850000
0!
1#
b10000000000000000 $
0C
1E
b10000000000000000 F
0G
b1 H
b1 Q
b1 R
#855000
1!
b1010101 7
1C
#860000
0!
0C
b10 H
b1010 ]
#865000
1!
b1010110 7
1C
#870000
0!
b11111111111110100000000000000000 $
0C
b11111111111110100000000000000000 F
b11 H
b1111111111111010 R
#875000
1!
b1010111 7
1C
#880000
0!
b1010000000000000000 $
b10000000000000000 %
1&
b1010111 8
0C
b1010000000000000000 F
1G
b100 H
b1111111111111010 J
b101 K
b10000 L
b101 M
b1 N
b0 O
b0 P
b101 R
b100 S
b100 T
b100 U
b10000 V
1W
b100 Y
b10000 [
0_
#885000
1!
b1011000 7
1C
#890000
0!
b0 %
b10000000000000000 3
0C
b10 Q
#895000
1!
b1011001 7
1C
#900000
0!
b1010000000000000000 %
0C
b11 Q
#905000
1!
b1011010 7
1C
#910000
0!
b0 %
b1010000000000000000 5
0C
b100 Q
#915000
1!
b1011011 7
1C
#920000
0!
0&
b1010 *
b1010 :
0C
0G
b0 H
b1 Q
#925000
1!
b1011100 7
1C
#930000
0!
0#
b11111111111111010000000000000000 -
b11111111111001000000000000000000 .
b11111111111111000000000000000000 /
b1110000000000000000 1
0C
0E
0G
b1 Q
#935000
1!
b1011101 7
1C
#940000
0!
1#
b10000000000000000 $
0C
1E
b10000000000000000 F
0G
b1 H
b1 Q
b1 R
#945000
1!
b1011110 7
1C
#950000
0!
0C
b10 H
b1011 ]
#955000
1!
b1011111 7
1C
#960000
0!
b11111111111111010000000000000000 $
0C
b11111111111111010000000000000000 F
b11 H
b1111111111111101 R
#965000
1!
b1100000 7
1C
#970000
0!
b11111111111001000000000000000000 $
b11111111111111000000000000000000 %
1&
b1100000 8
0C
b11111111111001000000000000000000 F
1G
b100 H
b1111111111111101 J
b1111111111100100 K
b1111001 L
b111 M
b1111111111111100 N
b0 O
b0 P
b1111111111100100 R
b1000 S
b1110 T
b1011 U
b1111001 V
1W
b1011 Y
b1111001 [
0_
#975000
1!
b1100001 7
1C
#980000
0!
b0 %
b11111111111111000000000000000000 3
0C
b10 Q
#985000
1!
b1100010 7
1C
#990000
0!
b1110000000000000000 %
0C
b11 Q
#995000
1!
b1100011 7
1C
#1000000
0!
b0 %
b1110000000000000000 5
0C
b100 Q
#1005000
1!
b1100100 7
1C
#1010000
0!
0&
b1011 *
b1011 :
0C
0G
b0 H
b1 Q
#1015000
1!
b1100101 7
1C
#1020000
0!
0#
b10010000000000000000 -
b100100000000000000000 .
b11111111111110100000000000000000 /
b11111111111111010000000000000000 1
0C
0E
0G
b1 Q
#1025000
1!
b1100110 7
1C
#1030000
0!
1#
b10000000000000000 $
0C
1E
b10000000000000000 F
0G
b1 H
b1 Q
b1 R
#1035000
1!
b1100111 7
1C
#1040000
0!
0C
b10 H
b1100 ]
#1045000
1!
b1101000 7
1C
#1050000
0!
b10010000000000000000 $
0C
b10010000000000000000 F
b11 H
b1001 R
#1055000
1!
b1101001 7
1C
#1060000
0!
b100100000000000000000 $
b11111111111110100000000000000000 %
1&
b1101001 8
0C
b100100000000000000000 F
1G
b100 H
b1001 J
b10010 K
b1001 L
b1111111111111101 M
b1111111111111010 N
b0 O
b0 P
b10010 R
b0 S
b110 T
b11 U
b1001 V
1W
b11 Y
b1001 [
0_
#1065000
1!
b1101010 7
1C
#1070000
0!
b0 %
b11111111111110100000000000000000 3
0C
b10 Q
#1075000
1!
b1101011 7
1C
#1080000
0!
b11111111111111010000000000000000 %
0C
b11 Q
#1085000
1!
b1101100 7
1C
#1090000
0!
b0 %
b11111111111111010000000000000000 5
0C
b100 Q
#1095000
1!
b1101101 7
1C
